pipeline_utils/__init__.py
pipeline_utils/__main__.py
pipeline_utils/lib/__init__.py
pipeline_utils/lib/check_lines.py
pipeline_utils/lib/yaml_parser.py
pipeline_utils/pipeline_deploy.py
pipeline_utils/schemas/__init__.py
pipeline_utils/schemas/schema.py
pipeline_utils/schemas/yaml_file_format.py
pipeline_utils/schemas/yaml_file_reference.py
pipeline_utils/schemas/yaml_metaworkflow.py
pipeline_utils/schemas/yaml_software.py
pipeline_utils/schemas/yaml_workflow.py
portal_pipeline_utils-3.0.0.dist-info/LICENSE
portal_pipeline_utils-3.0.0.dist-info/METADATA
portal_pipeline_utils-3.0.0.dist-info/WHEEL
portal_pipeline_utils-3.0.0.dist-info/entry_points.txt
portal_pipeline_utils-3.0.0.dist-info/RECORD
