Metadata-Version: 2.1
Name: portal-pipeline-utils
Version: 3.0.0
Summary: Utilities for deploying pipelines and interfacing with portal infrastructure.
Home-page: https://github.com/dbmi-bgm/portal-pipeline-utils
License: MIT
Author: Michele Berselli
Author-email: berselli.michele@gmail.com
Requires-Python: >=3.8,<3.12
Classifier: License :: OSI Approved :: MIT License
Classifier: Operating System :: POSIX :: Linux
Classifier: Programming Language :: Python
Classifier: Programming Language :: Python :: 3
Classifier: Programming Language :: Python :: 3.8
Classifier: Programming Language :: Python :: 3.9
Classifier: Programming Language :: Python :: 3.10
Classifier: Programming Language :: Python :: 3.11
Requires-Dist: awscli (>=1.29.62,<2.0.0)
Requires-Dist: boto3 (>=1.28.62,<2.0.0)
Requires-Dist: dcicutils (>=8.0.0,<9.0.0)
Requires-Dist: jsonschema (>=4.7.2,<5.0.0)
Requires-Dist: magma-suite (>=2.0.0,<3.0.0)
Project-URL: Repository, https://github.com/dbmi-bgm/portal-pipeline-utils
